Workbook
Name INVEST_PERFIL: 'Simulador_de Investimentos'!$C$35
Name investimento_mensal: 'Simulador_de Investimentos'!$D$18
Name patrimonio: 'Simulador_de Investimentos'!$D$21
Name PERFIL: 'Simulador_de Investimentos'!$C$34
Name Rendimento_carteira: 'Simulador_de Investimentos'!$J$13
Name salario: 'Simulador_de Investimentos'!$J$12
Name suges_Invest: 'Simulador_de Investimentos'!$J$14
Name taxa_mensal: 'Simulador_de Investimentos'!$D$20
Name tempo_investido: 'Simulador_de Investimentos'!$D$19

Sheet Simulador_de Investimentos
B11: CONFIGURAÇÕES
B12: Salário | J12: 6000
B13: Rendimento Carteira | J13: 0.006
B14: Sugestão de Investimento | J14: =J12*30% -> 1800
B17: INVESTIMENTO MENSAL
B18: Quanto investir por mês | D18: 1000
B19: Por quantos anos | D19: 10
B20: Qual a taxa de rendimento mensal | D20: 0.01079
B21: Quanto de patrimônio vai acumular | D21: =FV(taxa_mensal,tempo_investido*12,investimento_mensal*-1) -> 243284.21
B22: Quanto vai receber de dividendos por mês | D22: =patrimonio*Rendimento_carteira -> 1459.7053
B24: CENÁRIOS | D24: Dividendo
A25: 2 | B25: Quanto em 2 Anos? | C25: =FV($D$20,A25*12,$D$18*-1) -> 27227.627 | D25: =C25*Rendimento_carteira -> 163.36576
A26: 5 | B26: Quanto em 5 Anos? | C26: =FV($D$20,A26*12,$D$18*-1) -> 83776.914 | D26: =C26*Rendimento_carteira -> 502.66148
A27: 10 | B27: Quanto em 10 Anos? | C27: =FV($D$20,A27*12,$D$18*-1) -> 243284.21 | D27: =C27*Rendimento_carteira -> 1459.7053
A28: 20 | B28: Quanto em 20 Anos? | C28: =FV($D$20,A28*12,$D$18*-1) -> 1125198.4 | D28: =C28*Rendimento_carteira -> 6751.1904
A29: 30 | B29: Quanto em 30 Anos? | C29: =FV($D$20,A29*12,$D$18*-1) -> 4322169.7 | D29: =C29*Rendimento_carteira -> 25933.018
B34: Perfil | C34: Conservador
B35: VALOR A SER INVESTIDO POR MÊS | C35: 200
B37: TIPO DE FII | C37: Percentual Sugerido | D37: Valores
B38: PAPEL | C38: =VLOOKUP(PERFIL&"-"&B38,BASE!$A$2:$D$20,4,0) -> 0.3 | D38: =INVEST_PERFIL*C38 -> 60
B39: TIJOLO | C39: =VLOOKUP(PERFIL&"-"&B39,BASE!$A$2:$D$20,4,0) -> 0.5 | D39: =INVEST_PERFIL*C39 -> 100
B40: HIBRIDO | C40: =VLOOKUP(PERFIL&"-"&B40,BASE!$A$2:$D$20,4,0) -> 0.1 | D40: =INVEST_PERFIL*C40 -> 20
B41: FOFs | C41: =VLOOKUP(PERFIL&"-"&B41,BASE!$A$2:$D$20,4,0) -> 0.1 | D41: =INVEST_PERFIL*C41 -> 20
B42: DESENVOLVIMENTO | C42: =VLOOKUP(PERFIL&"-"&B42,BASE!$A$2:$D$20,4,0) -> 0 | D42: =INVEST_PERFIL*C42 -> 0
B43: HOTELARIAS | C43: =VLOOKUP(PERFIL&"-"&B43,BASE!$A$2:$D$20,4,0) -> 0 | D43: =INVEST_PERFIL*C43 -> 0
D44: =SUM(D38:D43) -> 200

Sheet BASE
A2: CHAVE | B2: PERFIL | C2: TIPO DE FII | D2: %
A3: =B3&"-"&C3 -> Conservador-PAPEL | B3: Conservador | C3: PAPEL | D3: 0.3
A4: =B4&"-"&C4 -> Conservador-TIJOLO | B4: Conservador | C4: TIJOLO | D4: 0.5
A5: =B5&"-"&C5 -> Conservador-HIBRIDO | B5: Conservador | C5: HIBRIDO | D5: 0.1
A6: =B6&"-"&C6 -> Conservador-FOFs | B6: Conservador | C6: FOFs | D6: 0.1
A7: =B7&"-"&C7 -> Conservador-DESENVOLVIMENTO | B7: Conservador | C7: DESENVOLVIMENTO | D7: 0
A8: =B8&"-"&C8 -> Conservador-HOTELARIAS | B8: Conservador | C8: HOTELARIAS | D8: 0
A9: =B9&"-"&C9 -> Moderado-PAPEL | B9: Moderado | C9: PAPEL | D9: 0.32
A10: =B10&"-"&C10 -> Moderado-TIJOLO | B10: Moderado | C10: TIJOLO | D10: 0.35
A11: =B11&"-"&C11 -> Moderado-HIBRIDO | B11: Moderado | C11: HIBRIDO | D11: 0.08
A12: =B12&"-"&C12 -> Moderado-FOFs | B12: Moderado | C12: FOFs | D12: 0.05
A13: =B13&"-"&C13 -> Moderado-DESENVOLVIMENTO | B13: Moderado | C13: DESENVOLVIMENTO | D13: 0.1
A14: =B14&"-"&C14 -> Moderado-HOTELARIAS | B14: Moderado | C14: HOTELARIAS | D14: 0.1
... A20: =B20&"-"&C20 -> Agressivo-HOTELARIAS | B20: Agressivo | C20: HOTELARIAS | D20: 0.1
